flatland/__init__.py
flatland/__main__.py
flatland/flatland_exceptions.py
flatland/log.conf
flatland/configuration/__init__.py
flatland/configuration/config.py
flatland/connector_subsystem/__init__.py
flatland/connector_subsystem/anchored_leaf_stem.py
flatland/connector_subsystem/anchored_stem.py
flatland/connector_subsystem/anchored_tree_stem.py
flatland/connector_subsystem/bending_binary_connector.py
flatland/connector_subsystem/binary_connector.py
flatland/connector_subsystem/branch.py
flatland/connector_subsystem/connector.py
flatland/connector_subsystem/connector_layout_specification.py
flatland/connector_subsystem/connector_type.py
flatland/connector_subsystem/decorated_stem.py
flatland/connector_subsystem/floating_binary_stem.py
flatland/connector_subsystem/floating_leaf_stem.py
flatland/connector_subsystem/floating_stem.py
flatland/connector_subsystem/grafted_branch.py
flatland/connector_subsystem/interpolated_branch.py
flatland/connector_subsystem/rendered_symbol.py
flatland/connector_subsystem/rut_branch.py
flatland/connector_subsystem/stem.py
flatland/connector_subsystem/stem_type.py
flatland/connector_subsystem/straight_binary_connector.py
flatland/connector_subsystem/tertiary_stem.py
flatland/connector_subsystem/tree_connector.py
flatland/connector_subsystem/trunk_stem.py
flatland/connector_subsystem/unary_connector.py
flatland/database/__init__.py
flatland/database/flatland.db
flatland/database/flatlanddb.py
flatland/database/relvars.py
flatland/database/population/__init__.py
flatland/database/population/connector/__init__.py
flatland/database/population/connector/annotation_instances.py
flatland/database/population/connector/connector_layout_specification_instances.py
flatland/database/population/connector/connector_style_instances.py
flatland/database/population/connector/connector_type_instances.py
flatland/database/population/connector/decorated_stem_instances.py
flatland/database/population/connector/name_spec_instances.py
flatland_model_diagram_editor-1.5.0.dist-info/LICENSE
flatland_model_diagram_editor-1.5.0.dist-info/METADATA
flatland_model_diagram_editor-1.5.0.dist-info/WHEEL
flatland_model_diagram_editor-1.5.0.dist-info/entry_points.txt
flatland_model_diagram_editor-1.5.0.dist-info/top_level.txt
flatland_model_diagram_editor-1.5.0.dist-info/RECORD
