Metadata-Version: 2.1
Name: flatland-model-diagram-editor
Version: 1.5.0
Summary: Model text file + layout text file -> beautiful diagram
Home-page: https://github.com/modelint/flatland-model-diagram-editor
Author: Leon Starr
Author-email: leon_starr@modelint.com
License: MIT
Platform: UNKNOWN
Classifier: License :: OSI Approved :: MIT License
Classifier: Programming Language :: Python
Classifier: Programming Language :: Python :: 3
Requires-Dist: pathlib
Requires-Dist: SQLAlchemy
Requires-Dist: pycairo
Requires-Dist: Arpeggio
Requires-Dist: numpy
Requires-Dist: PyYAML
